{
  "slice": 115,
  "idx_range": [2300, 2320],
  "task": "i18n: expandir a 7 idiomas (es/en/pt/fr/de/it/ja)",
  "report": "R17_I18N_EXPANDED.md",
  "file_modified": "volvix-i18n-wiring.js",
  "languages": ["es", "en", "pt", "fr", "de", "it", "ja"],
  "keys_per_language": 187,
  "total_translations": 1309,
  "new_translations": 748,
  "added_languages": ["fr", "de", "it", "ja"],
  "locales": {
    "es": "es-MX/MXN",
    "en": "en-US/USD",
    "pt": "pt-BR/BRL",
    "fr": "fr-FR/EUR",
    "de": "de-DE/EUR",
    "it": "it-IT/EUR",
    "ja": "ja-JP/JPY"
  },
  "flags": ["🇲🇽", "🇺🇸", "🇧🇷", "🇫🇷", "🇩🇪", "🇮🇹", "🇯🇵"],
  "utf8_verified": true,
  "intl_formatters": ["formatNumber", "formatCurrency", "formatDate", "formatDateTime"],
  "syntax_check": "node --check OK",
  "selector_floating": "7 idiomas con dropdown",
  "status": "done",
  "timestamp": "2026-04-26"
}
